.travis.yml
AUTHORS
ChangeLog
LICENSE
README.rst
mystartup.sh
requirements.txt
setup.cfg
setup.py
test.sh
Arduinozore.egg-info/PKG-INFO
Arduinozore.egg-info/SOURCES.txt
Arduinozore.egg-info/dependency_links.txt
Arduinozore.egg-info/entry_points.txt
Arduinozore.egg-info/not-zip-safe
Arduinozore.egg-info/pbr.json
Arduinozore.egg-info/requires.txt
Arduinozore.egg-info/top_level.txt
arduinozore/__init__.py
arduinozore/__main__.py
arduinozore/install_cert.sh
arduinozore/settings.py
arduinozore/static_installer.sh
arduinozore/urls.py
arduinozore/arduino/arduinozore/arduinozore.ino
arduinozore/handlers/README.rst
arduinozore/handlers/__init__.py
arduinozore/handlers/baseHandler.py
arduinozore/handlers/card.py
arduinozore/handlers/crudHandler.py
arduinozore/handlers/device.py
arduinozore/handlers/error404handler.py
arduinozore/handlers/index.py
arduinozore/handlers/sensor.py
arduinozore/handlers/serialManager.py
arduinozore/handlers/serialReader.py
arduinozore/handlers/setting.py
arduinozore/handlers/tools.py
arduinozore/handlers/ws.py
arduinozore/models/__init__.py
arduinozore/models/card.py
arduinozore/models/device.py
arduinozore/models/model.py
arduinozore/models/sensor.py
arduinozore/static/README.rst
arduinozore/templates/404.html
arduinozore/templates/README.rst
arduinozore/templates/base.html
arduinozore/templates/index.html
arduinozore/templates/settings.html
arduinozore/templates/card/card.html
arduinozore/templates/card/config.html
arduinozore/templates/card/list.html
arduinozore/templates/card/show.html
arduinozore/templates/device/communicate.html
arduinozore/templates/device/config.html
arduinozore/templates/device/device.html
arduinozore/templates/device/list.html
arduinozore/templates/device/show.html
arduinozore/templates/sensor/config.html
arduinozore/templates/sensor/list.html
arduinozore/templates/sensor/sensor.html
arduinozore/templates/sensor/show.html
doc/journalDeTravail/.latexmkrc
doc/journalDeTravail/Makefile
doc/journalDeTravail/journalDeTravail.pdf
doc/journalDeTravail/journalDeTravail.rst
doc/journalDeTravail/img/arduinozore.png
doc/journalDeTravail/img/logo.jpg
doc/journalDeTravail/tools/getMetadata.lua
doc/journalDeTravail/tools/md_filter.py
doc/journalDeTravail/tools/project_infos.yaml
