Metadata-Version: 1.1
Name: Arduinozore
Version: 1.1.3
Summary: Web server for arduino sensor visualization.
Home-page: https://github.com/S-Amiral/arduinozore
Author: André Neto da Silva, Laurent Gander & Maël Pedretti
Author-email: mael.pedretti@he-arc.ch
License: MIT
Platform: UNKNOWN
Classifier: Development Status :: 4 - Beta
Classifier: Environment :: Console
Classifier: Intended Audience :: Education
Classifier: Operating System :: MacOS :: MacOS X
Classifier: Operating System :: Microsoft :: Windows
Classifier: Operating System :: POSIX
Classifier: Programming Language :: Python :: 3 :: Only
Classifier: Programming Language :: Python :: 3.6
Classifier: Programming Language :: Python :: 3.5
Classifier: Programming Language :: Python :: 3.4
Classifier: Programming Language :: Python :: Implementation :: CPython
Classifier: Topic :: Home Automation
